stl_to_obj/__init__.py
stl_to_obj/__main__.py
stl_to_obj/stl_to_obj.py
stl_to_obj-1.0.0.dist-info/LICENSE
stl_to_obj-1.0.0.dist-info/METADATA
stl_to_obj-1.0.0.dist-info/WHEEL
stl_to_obj-1.0.0.dist-info/RECORD
