Metadata-Version: 2.1
Name: stl_to_obj
Version: 1.0.0
Summary: Converts a binary STL to OBJ
Home-page: https://github.com/jmanek/stl_to_obj
License: MIT
Author: Jesse Manek
Author-email: jesse.manek@gmail.com
Requires-Python: >=3.6,<4.0
Classifier: License :: OSI Approved :: MIT License
Classifier: Programming Language :: Python :: 3
Classifier: Programming Language :: Python :: 3.6
Classifier: Programming Language :: Python :: 3.7
Classifier: Programming Language :: Python :: 3.8
Classifier: Programming Language :: Python :: 3.9
Classifier: Programming Language :: Python :: 3.10
Classifier: Programming Language :: Python :: 3.11
Classifier: Programming Language :: Python :: 3.12
Project-URL: Repository, https://github.com/jmanek/stl_to_obj
